pycwt/__init__.py
pycwt/_version_.py
pycwt/helpers.py
pycwt/mothers.py
pycwt/wavelet.py
pycwt/sample/__init__.py
pycwt/sample/dataset.py
pycwt/sample/jao.dat
pycwt/sample/jbaltic.dat
pycwt/sample/mauna.dat
pycwt/sample/monsoon.dat
pycwt/sample/sample.py
pycwt/sample/sample_MAUNA.png
pycwt/sample/sample_MONSOON.png
pycwt/sample/sample_NINO3.png
pycwt/sample/sample_SOI.png
pycwt/sample/sample_SUNSPOTS.png
pycwt/sample/sample_xwt.py
pycwt/sample/simple_sample.py
pycwt/sample/soi.dat
pycwt/sample/sst_nino3.dat
pycwt/sample/sunspot.dat
pycwt-0.4.0b0.dist-info/LICENSE.rst
pycwt-0.4.0b0.dist-info/METADATA
pycwt-0.4.0b0.dist-info/WHEEL
pycwt-0.4.0b0.dist-info/top_level.txt
pycwt-0.4.0b0.dist-info/RECORD
