Metadata-Version: 2.1
Name: pycwt
Version: 0.4.0b0
Summary: Continuous wavelet transform module for Python.
Author: Nabil Freij, and contributors
Author-email: Sebastian Krieger <sebastian@nublia.com>
Maintainer-email: Sebastian Krieger <sebastian@nublia.com>
License: PyCWT is released under a BSD-style open source licence:
Project-URL: repository, https://github.com/regeirk/pycwt
Project-URL: documentation, https://pycwt.readthedocs.io/
Keywords: wavelet,spectral analysis,signal processing,data science,timeseries,time series
Classifier: Development Status :: 3 - Alpha
Classifier: License :: OSI Approved :: BSD License
Classifier: Programming Language :: Python
Classifier: Programming Language :: Python :: 3
Classifier: Operating System :: OS Independent
Classifier: Topic :: Software Development :: Libraries :: Python Modules
Classifier: Topic :: Utilities
Classifier: Intended Audience :: Science/Research
Requires-Python: >=3.8
License-File: LICENSE.rst
Requires-Dist: numpy (<2,>=1.24)
Requires-Dist: scipy (<2,>=1.10)
Requires-Dist: matplotlib (<4,>=3.7)
Requires-Dist: tqdm (<5,>=4.65)
